alex_ber_utils-0.13.11-py3.8-nspkg.pth
alexber/utils/__init__.py
alexber/utils/_ymlparsers_extra.py
alexber/utils/cache.py
alexber/utils/deploys.py
alexber/utils/emails.py
alexber/utils/fabs.py
alexber/utils/files.py
alexber/utils/importer.py
alexber/utils/in_memory_similarity_search.py
alexber/utils/init_app_conf.py
alexber/utils/inspects.py
alexber/utils/mains.py
alexber/utils/models.py
alexber/utils/parsers.py
alexber/utils/pprint.py
alexber/utils/processinvokes.py
alexber/utils/prof_to_callgrind.py
alexber/utils/props.py
alexber/utils/randoms.py
alexber/utils/setups.py
alexber/utils/stdlogging.py
alexber/utils/thread_locals.py
alexber/utils/uuids.py
alexber/utils/warning.py
alexber/utils/ymlparsers.py
alexber/utils/data/__init__.py
tests_data/__init__.py
tests_data/tests/__init__.py
tests_data/tests/utils/__init__.py
tests_data/tests/utils/config.properties
tests_data/tests/utils/config2.properties
tests_data/tests/utils/initappconf/__init__.py
tests_data/tests/utils/parser/__init__.py
tests_data/tests/utils/parser/config.ini
tests_data/tests/utils/ymlparsers/__init__.py
alex_ber_utils-0.13.11.dist-info/LICENSE.txt
alex_ber_utils-0.13.11.dist-info/METADATA
alex_ber_utils-0.13.11.dist-info/WHEEL
alex_ber_utils-0.13.11.dist-info/namespace_packages.txt
alex_ber_utils-0.13.11.dist-info/top_level.txt
alex_ber_utils-0.13.11.dist-info/RECORD
