Metadata-Version: 2.1
Name: alex-ber-utils
Version: 0.13.11
Summary: AlexBerUtils is collection of the small utilities
Home-page: https://github.com/alex-ber/AlexBerUtils
Author: Alexander Berkovich
License: Apache 2.0
Keywords: tools tool utils enum enums threadlocal UploadCommand upload uuid1mc uuid UUID UUID1 UUID4 UU1DMC issetdescriptor ismethod importer new_instance safe_eval is_empty parse_boolean Properties java.util.Properties
Classifier: Development Status :: 5 - Production/Stable
Classifier: Environment :: Console
Classifier: Intended Audience :: Developers
Classifier: Intended Audience :: Education
Classifier: License :: OSI Approved :: BSD License
Classifier: Programming Language :: Python
Classifier: Programming Language :: Python :: 3 :: Only
Classifier: Programming Language :: Python :: 3.8
Classifier: Programming Language :: Python :: 3.9
Classifier: Programming Language :: Python :: 3.10
Classifier: Programming Language :: Python :: 3.11
Classifier: Programming Language :: Python :: 3.12
Classifier: Programming Language :: Python :: Implementation :: CPython
Classifier: Topic :: Utilities
Classifier: Topic :: Software Development :: Libraries :: Python Modules
Classifier: Topic :: Desktop Environment
Classifier: Topic :: Education
Classifier: Operating System :: OS Independent
Classifier: Operating System :: Microsoft :: Windows
Classifier: Operating System :: POSIX
Classifier: Operating System :: Unix
Classifier: Natural Language :: English
Requires-Python: >=3.8
License-File: LICENSE.txt
Requires-Dist: pyyaml ==6.0.1
Provides-Extra: env
Requires-Dist: python-dotenv >=1.0.0 ; extra == 'env'
Provides-Extra: fabric
Requires-Dist: fabric >=2.5.0 ; extra == 'fabric'
Requires-Dist: pyOpenSSL >=23.3.0 ; extra == 'fabric'
Requires-Dist: cryptography >=41.0.7 ; extra == 'fabric'
Provides-Extra: np
Requires-Dist: numpy >=1.24.4 ; extra == 'np'
Provides-Extra: piptools
Requires-Dist: pip-tools >=7.3.0 ; extra == 'piptools'
Requires-Dist: packaging >=23.2 ; extra == 'piptools'
Provides-Extra: tests
Requires-Dist: exceptiongroup ==1.2.1 ; extra == 'tests'
Requires-Dist: iniconfig ==2.0.0 ; extra == 'tests'
Requires-Dist: packaging ==23.2 ; extra == 'tests'
Requires-Dist: pluggy ==1.5.0 ; extra == 'tests'
Requires-Dist: pytest ==7.4.3 ; extra == 'tests'
Requires-Dist: pytest-assume ==2.3.3 ; extra == 'tests'
Requires-Dist: pytest-asyncio ==0.21.1 ; extra == 'tests'
Requires-Dist: pytest-mock ==3.12.0 ; extra == 'tests'
Requires-Dist: pyyaml ==6.0.1 ; extra == 'tests'
Requires-Dist: tomli ==2.0.1 ; extra == 'tests'
Provides-Extra: yaml
Requires-Dist: PyYAML ; extra == 'yaml'
Requires-Dist: HiYaPyCo >=0.4.16 ; extra == 'yaml'
Requires-Dist: Jinja2 >1 ; extra == 'yaml'
Provides-Extra: yml
Requires-Dist: PyYAML ; extra == 'yml'
Requires-Dist: HiYaPyCo >=0.4.16 ; extra == 'yml'
Requires-Dist: Jinja2 >1 ; extra == 'yml'
